datacenter/__init__.py
datacenter/api.py
datacenter/config.py
datacenter/io_util.py
tests/__init__.py
tests/test2.py
tests/testProperty.py
tests/testapi.py
inf_datacenter_sdk-0.1.0.dist-info/METADATA
inf_datacenter_sdk-0.1.0.dist-info/WHEEL
inf_datacenter_sdk-0.1.0.dist-info/top_level.txt
inf_datacenter_sdk-0.1.0.dist-info/RECORD
