Metadata-Version: 2.1
Name: inf-datacenter-sdk
Version: 0.1.0
Author: zexiang
Requires-Dist: requests
Requires-Dist: dill
